{"skeleton":{"images":"../NullifiedKnightImages/"},
"bones":[{"name":"root"}],
"slots":[
	{"name":"Right_Thigh","bone":"root","attachment":"Right_Thigh"},
	{"name":"Right_Leg","bone":"root","attachment":"Right_Leg"},
	{"name":"Crotch","bone":"root","attachment":"Crotch"},
	{"name":"Ellipse 1","bone":"root","attachment":"Ellipse 1"},
	{"name":"Right_Lower_Arm","bone":"root","attachment":"Right_Lower_Arm"},
	{"name":"Left_Thigh","bone":"root","attachment":"Left_Thigh"},
	{"name":"Left_Leg","bone":"root","attachment":"Left_Leg"},
	{"name":"Right_Hand","bone":"root","attachment":"Right_Hand"},
	{"name":"Right_Shoulder","bone":"root","attachment":"Right_Shoulder"},
	{"name":"Chest","bone":"root","attachment":"Chest"},
	{"name":"Eye","bone":"root","attachment":"Eye"},
	{"name":"Left_Shoulder","bone":"root","attachment":"Left_Shoulder"},
	{"name":"Left_Lower_Arm","bone":"root","attachment":"Left_Lower_Arm"},
	{"name":"Left_handle","bone":"root","attachment":"Left_handle"},
	{"name":"Left_Hand","bone":"root","attachment":"Left_Hand"},
	{"name":"Armorshoulder","bone":"root","attachment":"Armorshoulder"},
	{"name":"Right_Shield","bone":"root","attachment":"Right_Shield"},
	{"name":"Left_Sword","bone":"root","attachment":"Left_Sword"}
],
"skins":{
	"default":{
		"Left_Sword":{"Left_Sword":{"x":3604,"y":3056,"width":1920,"height":584}},
		"Right_Shield":{"Right_Shield":{"x":4224,"y":2965,"width":566,"height":1846}},
		"Armorshoulder":{"Armorshoulder":{"x":2888.5,"y":3538,"width":643,"height":754}},
		"Left_Hand":{"Left_Hand":{"x":2425.5,"y":3089,"width":185,"height":200}},
		"Left_handle":{"Left_handle":{"x":2222,"y":3068,"width":860,"height":250}},
		"Left_Lower_Arm":{"Left_Lower_Arm":{"x":2264.5,"y":3372.5,"width":405,"height":885}},
		"Left_Shoulder":{"Left_Shoulder":{"x":2579.5,"y":3463.5,"width":575,"height":419}},
		"Eye":{"Eye":{"x":3257.5,"y":3629.5,"width":313,"height":363}},
		"Chest":{"Chest":{"x":3114.5,"y":3509.5,"width":489,"height":405}},
		"Right_Shoulder":{"Right_Shoulder":{"x":3584,"y":3254.5,"width":670,"height":655}},
		"Right_Hand":{"Right_Hand":{"x":4083,"y":3277.5,"width":172,"height":157}},
		"Left_Leg":{"Left_Leg":{"x":2494,"y":2405,"width":856,"height":930}},
		"Left_Thigh":{"Left_Thigh":{"x":2697.5,"y":2772.5,"width":339,"height":657}},
		"Right_Lower_Arm":{"Right_Lower_Arm":{"x":3942,"y":2965,"width":650,"height":596}},
		"Ellipse 1":{"Ellipse 1":{"x":3044.5,"y":3357.5,"width":573,"height":521}},
		"Crotch":{"Crotch":{"x":2920.5,"y":3089,"width":535,"height":484}},
		"Right_Leg":{"Right_Leg":{"x":3459.5,"y":2293,"width":681,"height":1012}},
		"Right_Thigh":{"Right_Thigh":{"x":3313.5,"y":2856,"width":563,"height":514}}
	}
},
"animations":{"animation":{}}
}